smarteo/__init__.py
smarteo-0.1.0.dist-info/LICENSE
smarteo-0.1.0.dist-info/METADATA
smarteo-0.1.0.dist-info/WHEEL
smarteo-0.1.0.dist-info/RECORD
